utcnow/cli/__init__.py
utcnow/cli/__main__.py
utcnow/cli/__version__.py
utcnow/cli/__version_data__.py
utcnow/cli/py.typed
utcnow_cli-1.0.0.dist-info/entry_points.txt
utcnow_cli-1.0.0.dist-info/LICENSE
utcnow_cli-1.0.0.dist-info/WHEEL
utcnow_cli-1.0.0.dist-info/METADATA
utcnow_cli-1.0.0.dist-info/RECORD
